django_sql_tagger/__init__.py
django_sql_tagger/apps.py
django_sql_tagger/tagging.py
django_sql_tagger/transaction.py
django_sql_tagger-0.3.1.dist-info/LICENSE
django_sql_tagger-0.3.1.dist-info/METADATA
django_sql_tagger-0.3.1.dist-info/WHEEL
django_sql_tagger-0.3.1.dist-info/top_level.txt
django_sql_tagger-0.3.1.dist-info/RECORD
