Metadata-Version: 2.1
Name: django-sql-tagger
Version: 0.3.1
Summary: Adds a comment to SQL queries pointing to their place of origin
Author-email: Filip Sedlák <filip@sedlakovi.org>
Project-URL: Homepage, https://github.com/monitora-media/django-sql-tagger
Classifier: Programming Language :: Python :: 3
Classifier: License :: OSI Approved :: GNU General Public License v3 (GPLv3)
Classifier: Operating System :: OS Independent
License-File: LICENSE
Requires-Dist: Django <6,>=4
Provides-Extra: dev
Requires-Dist: ipython ~=8.22.0 ; extra == 'dev'
Requires-Dist: pytest ~=8.0.1 ; extra == 'dev'
Requires-Dist: pytest-django ~=4.8.0 ; extra == 'dev'
